ln_jupyter_extra/_version.py
hewenbin_ln_jupyter_extra-0.1.29.data/data/share/jupyter/labextensions/hewenbin-ln-jupyter-extra/install.json
hewenbin_ln_jupyter_extra-0.1.29.dist-info/METADATA
hewenbin_ln_jupyter_extra-0.1.29.dist-info/WHEEL
hewenbin_ln_jupyter_extra-0.1.29.dist-info/licenses/LICENSE
hewenbin_ln_jupyter_extra-0.1.29.dist-info/RECORD
